aldryn_gallery/__init__.py
aldryn_gallery/cms_plugins.py
aldryn_gallery/compat.py
aldryn_gallery/forms.py
aldryn_gallery/models.py
aldryn_gallery/tests.py
aldryn_gallery/utils.py
aldryn_gallery/boilerplates/bootstrap3/templates/aldryn_gallery/plugins/gallery_base.html
aldryn_gallery/boilerplates/bootstrap3/templates/aldryn_gallery/plugins/standard/gallery.html
aldryn_gallery/boilerplates/bootstrap3/templates/aldryn_gallery/plugins/standard/image_slide.html
aldryn_gallery/boilerplates/bootstrap3/templates/aldryn_gallery/plugins/standard/slide.html
aldryn_gallery/boilerplates/bootstrap3/templates/aldryn_gallery/plugins/standard/slide_folder.html
aldryn_gallery/boilerplates/legacy/static/js/addons/cl.gallery.min.js
aldryn_gallery/boilerplates/legacy/static/js/libs/class.min.js
aldryn_gallery/boilerplates/legacy/templates/aldryn_gallery/base.html
aldryn_gallery/boilerplates/legacy/templates/aldryn_gallery/plugins/slide_folder.html
aldryn_gallery/boilerplates/legacy/templates/aldryn_gallery/plugins/feature/gallery.html
aldryn_gallery/boilerplates/legacy/templates/aldryn_gallery/plugins/feature/slide.html
aldryn_gallery/boilerplates/legacy/templates/aldryn_gallery/plugins/standard/gallery.html
aldryn_gallery/boilerplates/legacy/templates/aldryn_gallery/plugins/standard/slide.html
aldryn_gallery/migrations/0001_initial.py
aldryn_gallery/migrations/0002_galleryplugin_extra_styles.py
aldryn_gallery/migrations/0003_auto_20160821_1104.py
aldryn_gallery/migrations/__init__.py
aldryn_gallery/south_migrations/0001_initial.py
aldryn_gallery/south_migrations/0002_auto__add_field_slideplugin_url__add_field_slideplugin_page_link__add_.py
aldryn_gallery/south_migrations/0003_auto__chg_field_slideplugin_image.py
aldryn_gallery/south_migrations/0004_auto__add_slidefolderplugin.py
aldryn_gallery/south_migrations/0005_auto__add_field_slideplugin_link_text.py
aldryn_gallery/south_migrations/0006_auto__add_field_slideplugin_link_anchor.py
aldryn_gallery-0.5.0.dist-info/DESCRIPTION.rst
aldryn_gallery-0.5.0.dist-info/METADATA
aldryn_gallery-0.5.0.dist-info/RECORD
aldryn_gallery-0.5.0.dist-info/WHEEL
aldryn_gallery-0.5.0.dist-info/metadata.json
aldryn_gallery-0.5.0.dist-info/top_level.txt
