Metadata-Version: 2.0
Name: aldryn-gallery
Version: 0.5.0
Summary: Gallery
Home-page: https://github.com/aldryn/aldryn-gallery
Author: Divio AG
Author-email: info@divio.ch
License: LICENSE.txt
Platform: OS Independent
Classifier: Development Status :: 2 - Pre-Alpha
Classifier: Environment :: Web Environment
Classifier: Framework :: Django
Classifier: Intended Audience :: Developers
Classifier: License :: OSI Approved :: BSD License
Classifier: Operating System :: OS Independent
Classifier: Programming Language :: Python
Classifier: Topic :: Internet :: WWW/HTTP :: Dynamic Content
Classifier: Topic :: Software Development
Classifier: Topic :: Software Development :: Libraries :: Application Frameworks
Requires-Dist: aldryn-boilerplates (>=0.6)
Requires-Dist: django-filer
Requires-Dist: djangocms-text-ckeditor (>=2.1.2)
Requires-Dist: easy-thumbnails
